{"ID":11172,"Author":{"Name":"dsociative","ID":0,"FullName":"","Gravatar":"ded555ddcd8475821299d211ebc94a42"},"Title":"mysterious ansible","Description":"\u003cdiv class=\"content\"\u003e\u003cul\u003e\n\u003cli\u003eansible-playbook -i hosts docker_cloud.yml\u003c/li\u003e\n\u003cli\u003econnection error\u003c/li\u003e\n\u003cli\u003eansible -i hosts -u vagrant --private-key ~/.vagrant.d/insecure_private_key vagrant -m ping\u003c/li\u003e\n\u003cli\u003eok\u003c/li\u003e\n\u003cli\u003eansible-playbook -i hosts docker_cloud.yml\u003c/li\u003e\n\u003cli\u003e\u003cp\u003esuccess !\u003c/p\u003e\u003c/li\u003e\n\u003cli\u003e\u003cp\u003ewhy ???\u003c/p\u003e\u003c/li\u003e\n\u003cli\u003e\u003cp\u003ecached ssh key in ping command !\u003c/p\u003e\u003c/li\u003e\n\u003c/ul\u003e\n\u003c/div\u003e","Time":"2014-07-30T19:19:07Z","Tags":["OS X","zsh","xterm-256color"]}