[[0.074724,{"lines":{"0":[["                                                                                                                                                                                                                                 ",{}]],"1":[["                                                                                                                                                                                                                                 ",{}]],"2":[["                                                                                                                                                                                                                                 ",{}]],"3":[["                                                                                                                                                                                                                                 ",{}]],"4":[["                                                                                                                                                                                                                                 ",{}]],"5":[["                                                                                                                                                                                                                                 ",{}]],"6":[["                                                                                                                                                                                                                                 ",{}]],"7":[["                                                                                                                                                                                                                                 ",{}]],"8":[["                                                                                                                                                                                                                                 ",{}]],"9":[["                                                                                                                                                                                                                                 ",{}]],"10":[["                                                                                                                                                                                                                                 ",{}]],"11":[["                                                                                                                                                                                                                                 ",{}]],"12":[["                                                                                                                                                                                                                                 ",{}]],"13":[["                                                                                                                                                                                                                                 ",{}]],"14":[["                                                                                                                                                                                                                                 ",{}]],"15":[["                                                                                                                                                                                                                                 ",{}]],"16":[["                                                                                                                                                                                                                                 ",{}]],"17":[["                                                                                                                                                                                                                                 ",{}]],"18":[["                                                                                                                                                                                                                                 ",{}]],"19":[["                                                                                                                                                                                                                                 ",{}]],"20":[["                                                                                                                                                                                                                                 ",{}]],"21":[["                                                                                                                                                                                                                                 ",{}]],"22":[["                                                                                                                                                                                                                                 ",{}]],"23":[["                                                                                                                                                                                                                                 ",{}]],"24":[["                                                                                                                                                                                                                                 ",{}]],"25":[["                                                                                                                                                                                                                                 ",{}]],"26":[["                                                                                                                                                                                                                                 ",{}]],"27":[["                                                                                                                                                                                                                                 ",{}]],"28":[["                                                                                                                                                                                                                                 ",{}]],"29":[["                                                                                                                                                                                                                                 ",{}]],"30":[["                                                                                                                                                                                                                                 ",{}]],"31":[["                                                                                                                                                                                                                                 ",{}]],"32":[["                                                                                                                                                                                                                                 ",{}]],"33":[["                                                                                                                                                                                                                                 ",{}]],"34":[["                                                                                                                                                                                                                                 ",{}]],"35":[["                                                                                                                                                                                                                                 ",{}]],"36":[["                                                                                                                                                                                                                                 ",{}]],"37":[["                                                                                                                                                                                                                                 ",{}]],"38":[["                                                                                                                                                                                                                                 ",{}]],"39":[["                                                                                                                                                                                                                                 ",{}]],"40":[["                                                                                                                                                                                                                                 ",{}]],"41":[["                                                                                                                                                                                                                                 ",{}]],"42":[["                                                                                                                                                                                                                                 ",{}]],"43":[["                                                                                                                                                                                                                                 ",{}]],"44":[["                                                                                                                                                                                                                                 ",{}]],"45":[["                                                                                                                                                                                                                                 ",{}]],"46":[["                                                                                                                                                                                                                                 ",{}]],"47":[["                                                                                                                                                                                                                                 ",{}]],"48":[["                                                                                                                                                                                                                                 ",{}]],"49":[["                                                                                                                                                                                                                                 ",{}]],"50":[["                                                                                                                                                                                                                                 ",{}]],"51":[["                                                                                                                                                                                                                                 ",{}]],"52":[["                                                                                                                                                                                                                                 ",{}]],"53":[["                                                                                                                                                                                                                                 ",{}]],"54":[["                                                                                                                                                                                                                                 ",{}]],"55":[["                                                                                                                                                                                                                                 ",{}]],"56":[["                                                                                                                                                                                                                                 ",{}]]},"cursor":{"x":0,"y":0,"visible":true}}],[0.013097,{"lines":{"0":[["tstein",{"fg":4,"bold":true}],["@w530-tstein ",{}],["~ ",{"bold":true}],["%                                                                                                                                                                                                           ",{}]]},"cursor":{"x":23}}],[4.486588,{}],[0.007436,{"lines":{"1":[["tstein",{"fg":4,"bold":true}],["@w530-tstein ",{}],["~ ",{"bold":true}],["%                                                                                                                                                                                                           ",{}]]},"cursor":{"y":1}}],[0.524192,{}],[0.007373999999999999,{"lines":{"2":[["tstein",{"fg":4,"bold":true}],["@w530-tstein ",{}],["~ ",{"bold":true}],["%                                                                                                                                                                                                           ",{}]]},"cursor":{"y":2}}],[0.141832,{"cursor":{"x":0,"y":3}}],[0.007241000000000001,{"lines":{"3":[["tstein",{"fg":4,"bold":true}],["@w530-tstein ",{}],["~ ",{"bold":true}],["%                                                                                                                                                                                                           ",{}]]},"cursor":{"x":23}}],[0.142334,{"cursor":{"x":0,"y":4}}],[0.008022999999999999,{"lines":{"4":[["tstein",{"fg":4,"bold":true}],["@w530-tstein ",{}],["~ ",{"bold":true}],["%                                                                                                                                                                                                           ",{}]]},"cursor":{"x":23}}],[0.613282,{"lines":{"4":[["tstein",{"fg":4,"bold":true}],["@w530-tstein ",{}],["~ ",{"bold":true}],["% l                                                                                                                                                                                                         ",{}]]},"cursor":{"x":24}}],[0.07596,{"lines":{"4":[["tstein",{"fg":4,"bold":true}],["@w530-tstein ",{}],["~ ",{"bold":true}],["% ls                                                                                                                                                                                                        ",{}]]},"cursor":{"x":25}}],[0.248917,{"cursor":{"x":0,"y":5}}],[0.008167000000000001,{"lines":{"5":[["Audiobooks",{"fg":4,"bold":true}],["/      check_drbd  ",{}],["Downloads",{"fg":4,"bold":true}],["/          ",{}],["kernel",{"fg":4,"bold":true}],["/  mail.txt       ",{}],["network-manager-l2tp_0.9.8.5-0trusty1_amd64.deb",{"fg":1,"bold":true}],["  ",{}],["Podcasts",{"fg":4,"bold":true}],["/       ",{}],["Steam",{"fg":4,"bold":true}],["/                test       ",{}],["workspace",{"fg":4,"bold":true}],["/                                            ",{}]],"6":[["#.bash_history#  doc         hs_err_pid6219.log  konsole  ",{}],["Musik",{"fg":4,"bold":true}],["/         ",{}],["Öffentlich",{"fg":4,"bold":true}],["/                                      ",{}],["Schreibtisch",{"fg":4,"bold":true}],["/   suse_register-d3.log  ",{}],["Videos",{"fg":4,"bold":true}],["/                                                          ",{}]],"7":[["Bilder",{"fg":4,"bold":true}],["/          ",{}],["Dokumente",{"fg":4,"bold":true}],["/  ",{}],["jdownloader",{"fg":4,"bold":true}],["/        ",{}],["LaTeX",{"fg":4,"bold":true}],["/   mysqltuner.pl  ",{}],["opt",{"fg":4,"bold":true}],["/                                             sgrube_rsa.pub  ",{}],["target",{"fg":4,"bg":2}],["/               ",{}],["Vorlagen",{"fg":4,"bold":true}],["/                                                        ",{}]],"8":[["tstein",{"fg":4,"bold":true}],["@w530-tstein ",{}],["~ ",{"bold":true}],["%                                                                                                                                                                                                           ",{}]]},"cursor":{"x":23,"y":8}}],[3.600289,{"cursor":{"x":0,"y":9}}]]